README.md
setup.py
pymiere/__init__.py
pymiere/core.py
pymiere/exe_utils.py
pymiere/utils.py
pymiere/wrappers.py
pymiere.egg-info/PKG-INFO
pymiere.egg-info/SOURCES.txt
pymiere.egg-info/dependency_links.txt
pymiere.egg-info/requires.txt
pymiere.egg-info/top_level.txt
pymiere/objects/__init__.py
pymiere/objects/premiere_objects.py
pymiere/objects/start_vars.py