Metadata-Version: 2.1
Name: pymiere
Version: 1.1.0
Summary: Pythonic automations for Adobe Premiere Pro. Require the `Pymiere Link` extension for Premiere (installed separately).
Home-page: https://github.com/qmasingarbe/pymiere
Author: Quentin Masingarbe
Author-email: q.masingarbe@gmail.com
License: GNU
Keywords: pymiere,video,Premiere,Adobe,Pymiere,workflow,automation,Creative Cloud,edit,editor,editing,prproj,premiere pro
Platform: UNKNOWN
Classifier: Development Status :: 4 - Beta
Classifier: Intended Audience :: Developers
Classifier: License :: OSI Approved :: GNU General Public License v3 (GPLv3)
Classifier: Natural Language :: English
Classifier: Operating System :: Microsoft :: Windows
Classifier: Operating System :: MacOS
Classifier: Programming Language :: Python :: 2.7
Classifier: Programming Language :: Python :: 3.6
Classifier: Programming Language :: Python :: 3.7
Classifier: Programming Language :: Python :: 3.8
Classifier: Programming Language :: Python :: 3.9
Classifier: Topic :: Multimedia :: Video
Classifier: Topic :: Multimedia :: Video :: Non-Linear Editor
